odoo10_addon_hr_employee_lastnames-10.0.2.0.0-nspkg.pth
odoo/addons/hr_employee_lastnames/README.rst
odoo/addons/hr_employee_lastnames/__init__.py
odoo/addons/hr_employee_lastnames/__manifest__.py
odoo/addons/hr_employee_lastnames/hook.py
odoo/addons/hr_employee_lastnames/i18n/es.po
odoo/addons/hr_employee_lastnames/i18n/hr_employee_lastnames.pot
odoo/addons/hr_employee_lastnames/models/__init__.py
odoo/addons/hr_employee_lastnames/models/hr_employee.py
odoo/addons/hr_employee_lastnames/readme/CONTRIBUTORS.rst
odoo/addons/hr_employee_lastnames/readme/DESCRIPTION.rst
odoo/addons/hr_employee_lastnames/readme/USAGE.rst
odoo/addons/hr_employee_lastnames/static/description/icon.png
odoo/addons/hr_employee_lastnames/static/description/index.html
odoo/addons/hr_employee_lastnames/tests/__init__.py
odoo/addons/hr_employee_lastnames/tests/test_hr_employee_lastnames.py
odoo/addons/hr_employee_lastnames/views/hr_views.xml
odoo10_addon_hr_employee_lastnames-10.0.2.0.0.dist-info/METADATA
odoo10_addon_hr_employee_lastnames-10.0.2.0.0.dist-info/WHEEL
odoo10_addon_hr_employee_lastnames-10.0.2.0.0.dist-info/namespace_packages.txt
odoo10_addon_hr_employee_lastnames-10.0.2.0.0.dist-info/top_level.txt
odoo10_addon_hr_employee_lastnames-10.0.2.0.0.dist-info/RECORD
